{
  "db_name": "SQLite",
  "query": "SELECT id as `id!`, username, role, created_at, updated_at FROM users WHERE id = ?",
  "describe": {
    "columns": [
      {
        "name": "id!",
        "ordinal": 0,
        "type_info": "Int64"
      },
      {
        "name": "username",
        "ordinal": 1,
        "type_info": "Text"
      },
      {
        "name": "role",
        "ordinal": 2,
        "type_info": "Text"
      },
      {
        "name": "created_at",
        "ordinal": 3,
        "type_info": "Datetime"
      },
      {
        "name": "updated_at",
        "ordinal": 4,
        "type_info": "Datetime"
      }
    ],
    "parameters": {
      "Right": 1
    },
    "nullable": [
      false,
      false,
      false,
      false,
      false
    ]
  },
  "hash": "bac240f33b835527abc89d530523b44eed73fbed5b2d13e20d864004e94a6a4c"
}
